graphql_generate/__init__.py
graphql_generate/support.py
ldata-fuse/__init__.py
ldata-fuse/__main__.py
ldata-fuse/app.py
ldata-fuse/config.py
ldata-fuse/intervals.py
queries_lib/main.py
queries_lib/schema.py
ldata_fuse-0.1.25.dist-info/METADATA
ldata_fuse-0.1.25.dist-info/WHEEL
ldata_fuse-0.1.25.dist-info/RECORD
